<Localization>
	<Title>English</Title>
	<Entry key="olypsum">Olypsum</Entry>
	<Entry key="loading">Loading ...</Entry>
	<Entry key="saveGames">Savegames</Entry>
	<Entry key="multiplayer">Multiplayer</Entry>
	<Entry key="options">Options</Entry>
	<Entry key="credits">Credits</Entry>
	<Entry key="quitGame">Quit Game</Entry>
	<Entry key="back">Back</Entry>
	<Entry key="mainMenu">Main Menu</Entry>
	<Entry key="graphics">Graphics</Entry>
	<Entry key="language">Language</Entry>
	<Entry key="sound">Sound</Entry>
	<Entry key="soundGlobal">Volume</Entry>
	<Entry key="soundMusic">Music</Entry>
	<Entry key="fullScreenEnabled">Full Screen</Entry>
	<Entry key="edgeSmoothEnabled">Antialiasing</Entry>
	<Entry key="cubemapsEnabled">Cubemaps</Entry>
	<Entry key="screenBlurEnabled">Screen Blur</Entry>
	<Entry key="depthOfFieldQuality">Depth Of Field</Entry>
	<Entry key="vSyncEnabled">V-Sync</Entry>
	<Entry key="bumpMappingQuality">Surface Quality</Entry>
	<Entry key="shadowQuality">Shadow Quality</Entry>
	<Entry key="ssaoQuality">SSAO Quality</Entry>
	<Entry key="blendingQuality">Blending Quality</Entry>
	<Entry key="on">On</Entry>
	<Entry key="off">Off</Entry>
	<Entry key="cancel">Cancel</Entry>
	<Entry key="ok">Ok</Entry>
	<Entry key="name">Name</Entry>
	<Entry key="newGame">New Game</Entry>
	<Entry key="removeGame">Remove Game</Entry>
</Localization>